[
  {
    "Id": "55a3d71c-bd97-4adc-9ac9-a78a39f5f537",
    "FirstName": "Zyumbyula",
    "LastName": "Svetkova",
    "CV": null,
    "LocationId": null,
    "PhoneNumberId": null,
    "SexValue": "Female"
  },
  {
    "Id": "e91fa5a5-7a31-40b3-aa82-af79a9a9c23d",
    "FirstName": "Darina",
    "LastName": "Valerieva",
    "CV": null,
    "LocationId": null,
    "PhoneNumberId": null,
    "SexValue": "Female"
  },
  {
    "Id": "07e18758-b594-44dc-9ac2-2f5d162d1dc4",
    "FirstName": "Ivana",
    "LastName": "Glavcheva",
    "CV": null,
    "LocationId": null,
    "PhoneNumberId": null,
    "SexValue": "Female"
  },
  {
    "Id": "7023a048-3512-43f2-81ab-8e70b72f05bb",
    "FirstName": "Krasimira",
    "LastName": "Velichkova",
    "CV": null,
    "LocationId": null,
    "PhoneNumberId": null,
    "SexValue": "Female"
  },
  {
    "Id": "de832038-20df-49ba-bd83-a2732fefd908",
    "FirstName": "Gera",
    "LastName": "Tsvetkova",
    "CV": null,
    "LocationId": null,
    "PhoneNumberId": null,
    "SexValue": "Female"
  },
  {
    "Id": "839310ff-c901-44d1-9eff-7305a0920847",
    "FirstName": "Iskra",
    "LastName": "Buneva",
    "CV": null,
    "LocationId": null,
    "PhoneNumberId": null,
    "SexValue": "Female"
  },
  {
    "Id": "5e994a2c-0876-455b-aeb6-9d8bc6fdfd77",
    "FirstName": "Tsvetelina",
    "LastName": "Velikova",
    "CV": null,
    "LocationId": null,
    "PhoneNumberId": null,
    "SexValue": "Female"
  },
  {
    "Id": "8ea514b8-c405-4e82-b4fc-7c14f0176abb",
    "FirstName": "Blaga",
    "LastName": "Ivanova",
    "CV": null,
    "LocationId": null,
    "PhoneNumberId": null,
    "SexValue": "Female"
  },
  {
    "Id": "45ea16d3-7a48-4bbe-9d52-5ba4629ab0a9",
    "FirstName": "Darina",
    "LastName": "Nankova",
    "CV": null,
    "LocationId": null,
    "PhoneNumberId": null,
    "SexValue": "Female"
  },
  {
    "Id": "8be87f81-5d04-4bbc-a1a4-8012bfe00326",
    "FirstName": "Yordanka",
    "LastName": "Nikolova",
    "CV": null,
    "LocationId": null,
    "PhoneNumberId": null,
    "SexValue": "Female"
  },
  {
    "Id": "73291ad1-7d6c-4f0e-8f4a-10b01b193d6c",
    "FirstName": "Kaloyan",
    "LastName": "Todorov",
    "CV": null,
    "LocationId": null,
    "PhoneNumberId": null,
    "SexValue": "Male"
  },
  {
    "Id": "1cc2a7b3-4708-414a-9715-7ff1fc8bca49",
    "FirstName": "Zmeyo",
    "LastName": "Nakov",
    "CV": null,
    "LocationId": null,
    "PhoneNumberId": null,
    "SexValue": "Male"
  },
  {
    "Id": "5ea82433-fe6b-4f64-9d24-299787396a41",
    "FirstName": "Zhito",
    "LastName": "Kynev",
    "CV": null,
    "LocationId": null,
    "PhoneNumberId": null,
    "SexValue": "Male"
  },
  {
    "Id": "d65c40c3-e4cd-4ec8-8f19-af57caf406d9",
    "FirstName": "Velizar",
    "LastName": "Lukanov",
    "CV": null,
    "LocationId": null,
    "PhoneNumberId": null,
    "SexValue": "Male"
  },
  {
    "Id": "f070b443-ada7-41d7-aea2-7aff3108638a",
    "FirstName": "Spas",
    "LastName": "Botev",
    "CV": null,
    "LocationId": null,
    "PhoneNumberId": null,
    "SexValue": "Male"
  },
  {
    "Id": "c23c6d3f-e1a1-49a4-a959-b7f69f56e3c2",
    "FirstName": "Yanko",
    "LastName": "Popov",
    "CV": null,
    "LocationId": null,
    "PhoneNumberId": null,
    "SexValue": "Male"
  },
  {
    "Id": "d9e71500-2335-495f-8290-7bb7c2b97324",
    "FirstName": "Zheko",
    "LastName": "Nikolov",
    "CV": null,
    "LocationId": null,
    "PhoneNumberId": null,
    "SexValue": "Male"
  },
  {
    "Id": "2cca8680-e298-457c-94df-6de1c9774e8d",
    "FirstName": "Itzo",
    "LastName": "Valov",
    "CV": null,
    "LocationId": null,
    "PhoneNumberId": null,
    "SexValue": "Male"
  },
  {
    "Id": "033d12be-7be3-41cd-9467-e81c57736fd7",
    "FirstName": "Gavrail",
    "LastName": "Stoev",
    "CV": null,
    "LocationId": null,
    "PhoneNumberId": null,
    "SexValue": "Male"
  },
  {
    "Id": "738346e9-fa96-4960-8b12-fdb8593e8a19",
    "FirstName": "Grigori",
    "LastName": "Varbanov",
    "CV": null,
    "LocationId": null,
    "PhoneNumberId": null,
    "SexValue": "Male"
  }
]